Metadata-Version: 2.1
Name: conciliator-python
Version: 0.0.2
Summary: Python library for the Conciliator API
Home-page: https://github.com/dhatim/conciliator-python
Author: Dhatim
Author-email: contact@dhatim.com
License: Apache Software License
Download-URL: https://github.com/dhatim/conciliator-python/archive/refs/tags/0.0.2.tar.gz
Keywords: conciliator,client,api,python
Platform: UNKNOWN
Classifier: Programming Language :: Python :: 3
Classifier: License :: OSI Approved :: Apache Software License
Classifier: Operating System :: OS Independent
Requires-Python: >=3.6
